dictvars/__init__.py
dictvars-0.2.0.dist-info/LICENSE.txt
dictvars-0.2.0.dist-info/METADATA
dictvars-0.2.0.dist-info/WHEEL
dictvars-0.2.0.dist-info/top_level.txt
dictvars-0.2.0.dist-info/zip-safe
dictvars-0.2.0.dist-info/RECORD
